singleton/__init__.py
singleton/singleton.py
alexeyqu_singleton-0.0.1.dist-info/LICENSE
alexeyqu_singleton-0.0.1.dist-info/METADATA
alexeyqu_singleton-0.0.1.dist-info/WHEEL
alexeyqu_singleton-0.0.1.dist-info/top_level.txt
alexeyqu_singleton-0.0.1.dist-info/RECORD
