Metadata-Version: 2.1
Name: alexeyqu-singleton
Version: 0.0.1
Summary: alexeyqu likes this singleton.
Home-page: https://github.com/alexeyqu/singleton
Author: Alex Kulikov
License: UNKNOWN
Project-URL: Bug Tracker, https://github.com/alexeyqu/singleton/issues
Platform: UNKNOWN
Classifier: Programming Language :: Python :: 3
Classifier: License :: OSI Approved :: MIT License
Classifier: Operating System :: OS Independent
Requires-Python: >=3.0
License-File: LICENSE
